accelphys/__init__.py
accelphys/formulas.py
src/__init__.py
src/formulas.py
accelphys-0.1.0.dist-info/LICENSE
accelphys-0.1.0.dist-info/METADATA
accelphys-0.1.0.dist-info/WHEEL
accelphys-0.1.0.dist-info/top_level.txt
accelphys-0.1.0.dist-info/RECORD
