Metadata-Version: 2.1
Name: accelphys
Version: 0.1.0
Summary: Accelerator Physics
Home-page: https://github.com/jako4295/accelphys
Author: Jakob Olsen
Author-email: jakob.olsen@cern.ch
Classifier: Programming Language :: Python :: 3
Classifier: Operating System :: OS Independent
Requires-Python: ~=3.11.0
License-File: LICENSE
Requires-Dist: numpy
Requires-Dist: scipy
Provides-Extra: all
Requires-Dist: numpy ; extra == 'all'
Requires-Dist: scipy ; extra == 'all'
Provides-Extra: core
Requires-Dist: numpy ; extra == 'core'
Requires-Dist: scipy ; extra == 'core'
Provides-Extra: dev
Provides-Extra: doc
Provides-Extra: test
